mke3d/__init__.py
mke3d/actor.py
mke3d/camera.py
mke3d/classes.py
mke3d/core.py
mke3d/hud.py
mke3d/light.py
mke3d/meshes.py
mke3d/methods.py
mke3d/exemple_textures/planet_texture_1.png
mke3d/exemple_textures/planet_texture_2.png
mke3d/exemple_textures/sun_texture.png
mke3d/fonts/default.ttf
mke3d/fonts/default_2.ttf
mke3d/fonts/game_console.ttf
mke3d-0.1.6.dist-info/LICENSE
mke3d-0.1.6.dist-info/METADATA
mke3d-0.1.6.dist-info/WHEEL
mke3d-0.1.6.dist-info/top_level.txt
mke3d-0.1.6.dist-info/RECORD
