Metadata-Version: 2.2
Name: mke3d
Version: 0.1.6
Summary: Basic 3D Engine with OpenGL
Home-page: https://github.com/mk-samoilov/3D-Engine
Author: Mk Smlv
Author-email: me@mk-samoilov.ru
Classifier: Programming Language :: Python :: 3
Classifier: License :: OSI Approved :: MIT License
Classifier: Operating System :: OS Independent
Requires-Python: >=3.6
License-File: LICENSE
Requires-Dist: PyOpenGL
Requires-Dist: pygame
Requires-Dist: numpy
Requires-Dist: Pillow
Dynamic: author
Dynamic: author-email
Dynamic: classifier
Dynamic: description
Dynamic: description-content-type
Dynamic: home-page
Dynamic: requires-dist
Dynamic: requires-python
Dynamic: summary
